django_expvar_resource-0.1.0.dist-info/DESCRIPTION.rst
django_expvar_resource-0.1.0.dist-info/METADATA
django_expvar_resource-0.1.0.dist-info/RECORD
django_expvar_resource-0.1.0.dist-info/WHEEL
django_expvar_resource-0.1.0.dist-info/metadata.json
django_expvar_resource-0.1.0.dist-info/top_level.txt
expvarresource/__init__.py
expvarresource/models.py
expvarresource/vars.py
